{"minecraft:recipes/decorations/crafting_table":{"criteria":{"unlock_right_away":"2025-04-30 23:41:39 +0000"},"done":true},"minecraft:adventure/adventuring_time":{"criteria":{"minecraft:deep_cold_ocean":"2025-04-30 23:49:22 +0000","minecraft:beach":"2025-04-30 23:42:54 +0000","minecraft:dark_forest":"2025-04-30 23:42:55 +0000","minecraft:forest":"2025-04-30 23:42:12 +0000","minecraft:taiga":"2025-05-01 03:40:10 +0000","minecraft:mangrove_swamp":"2025-04-30 23:41:40 +0000","minecraft:jungle":"2025-04-30 23:42:38 +0000","minecraft:river":"2025-04-30 23:42:27 +0000","minecraft:swamp":"2025-05-01 03:41:22 +0000","minecraft:stony_shore":"2025-05-01 03:40:19 +0000"},"done":false},"minecraft:recipes/transportation/mangrove_boat":{"criteria":{"in_water":"2025-04-30 23:47:32 +0000"},"done":true},"minecraft:recipes/transportation/acacia_boat":{"criteria":{"in_water":"2025-04-30 23:47:32 +0000"},"done":true},"minecraft:recipes/transportation/cherry_boat":{"criteria":{"in_water":"2025-04-30 23:47:32 +0000"},"done":true},"minecraft:recipes/transportation/bamboo_raft":{"criteria":{"in_water":"2025-04-30 23:47:32 +0000"},"done":true},"minecraft:recipes/transportation/spruce_boat":{"criteria":{"in_water":"2025-04-30 23:47:32 +0000"},"done":true},"minecraft:recipes/transportation/birch_boat":{"criteria":{"in_water":"2025-04-30 23:47:32 +0000"},"done":true},"minecraft:recipes/transportation/oak_boat":{"criteria":{"in_water":"2025-04-30 23:47:32 +0000"},"done":true},"minecraft:recipes/transportation/jungle_boat":{"criteria":{"in_water":"2025-04-30 23:47:32 +0000"},"done":true},"minecraft:recipes/transportation/dark_oak_boat":{"criteria":{"in_water":"2025-04-30 23:47:32 +0000"},"done":true},"minecraft:recipes/decorations/light_blue_stained_glass_pane":{"criteria":{"has_glass":"2025-04-30 23:47:53 +0000"},"done":true},"minecraft:recipes/building_blocks/quartz_stairs":{"criteria":{"has_quartz_block":"2025-04-30 23:56:19 +0000"},"done":true},"minecraft:recipes/building_blocks/smooth_quartz":{"criteria":{"has_quartz_block":"2025-04-30 23:56:19 +0000"},"done":true},"minecraft:recipes/building_blocks/quartz_slab":{"criteria":{"has_quartz_block":"2025-04-30 23:56:19 +0000"},"done":true},"minecraft:recipes/building_blocks/chiseled_quartz_block":{"criteria":{"has_quartz_block":"2025-04-30 23:56:19 +0000"},"done":true},"minecraft:recipes/building_blocks/quartz_bricks":{"criteria":{"has_quartz_block":"2025-04-30 23:56:19 +0000"},"done":true},"minecraft:recipes/building_blocks/quartz_bricks_from_quartz_block_stonecutting":{"criteria":{"has_quartz_block":"2025-04-30 23:56:19 +0000"},"done":true},"minecraft:recipes/building_blocks/chiseled_quartz_block_from_quartz_block_stonecutting":{"criteria":{"has_quartz_block":"2025-04-30 23:56:19 +0000"},"done":true},"minecraft:recipes/building_blocks/quartz_pillar_from_quartz_block_stonecutting":{"criteria":{"has_quartz_block":"2025-04-30 23:56:19 +0000"},"done":true},"minecraft:recipes/building_blocks/quartz_slab_from_stonecutting":{"criteria":{"has_quartz_block":"2025-04-30 23:56:19 +0000"},"done":true},"minecraft:recipes/building_blocks/quartz_pillar":{"criteria":{"has_quartz_block":"2025-04-30 23:56:19 +0000"},"done":true},"minecraft:recipes/building_blocks/quartz_stairs_from_quartz_block_stonecutting":{"criteria":{"has_quartz_block":"2025-04-30 23:56:19 +0000"},"done":true},"minecraft:recipes/building_blocks/smooth_quartz_slab_from_smooth_quartz_stonecutting":{"criteria":{"has_smooth_quartz":"2025-04-30 23:56:49 +0000"},"done":true},"minecraft:recipes/building_blocks/smooth_quartz_slab":{"criteria":{"has_smooth_quartz":"2025-04-30 23:56:49 +0000"},"done":true},"minecraft:recipes/building_blocks/smooth_quartz_stairs":{"criteria":{"has_smooth_quartz":"2025-04-30 23:56:49 +0000"},"done":true},"minecraft:recipes/building_blocks/smooth_quartz_stairs_from_smooth_quartz_stonecutting":{"criteria":{"has_smooth_quartz":"2025-04-30 23:56:49 +0000"},"done":true},"minecraft:recipes/decorations/chest":{"criteria":{"has_lots_of_items":"2025-05-01 03:39:49 +0000"},"done":true},"minecraft:recipes/food/suspicious_stew_from_poppy":{"criteria":{"has_poppy":"2025-05-01 03:39:49 +0000"},"done":true},"minecraft:recipes/misc/red_dye_from_poppy":{"criteria":{"has_poppy":"2025-05-01 03:39:49 +0000"},"done":true},"minecraft:recipes/misc/charcoal":{"criteria":{"has_log":"2025-05-01 03:42:27 +0000"},"done":true},"minecraft:recipes/building_blocks/oak_planks":{"criteria":{"has_logs":"2025-05-01 03:42:27 +0000"},"done":true},"minecraft:recipes/building_blocks/oak_wood":{"criteria":{"has_log":"2025-05-01 03:42:27 +0000"},"done":true},"minecraft:recipes/building_blocks/birch_planks":{"criteria":{"has_logs":"2025-05-02 21:22:40 +0000"},"done":true},"minecraft:recipes/building_blocks/birch_wood":{"criteria":{"has_log":"2025-05-02 21:22:40 +0000"},"done":true},"minecraft:recipes/building_blocks/spruce_planks":{"criteria":{"has_logs":"2025-05-02 21:24:33 +0000"},"done":true},"minecraft:recipes/building_blocks/spruce_wood":{"criteria":{"has_log":"2025-05-02 21:24:33 +0000"},"done":true},"minecraft:recipes/decorations/ladder":{"criteria":{"has_stick":"2025-05-02 21:59:31 +0000"},"done":true},"minecraft:recipes/decorations/campfire":{"criteria":{"has_stick":"2025-05-02 21:59:31 +0000"},"done":true},"minecraft:recipes/tools/wooden_hoe":{"criteria":{"has_stick":"2025-05-02 21:59:31 +0000"},"done":true},"minecraft:recipes/tools/wooden_pickaxe":{"criteria":{"has_stick":"2025-05-02 21:59:31 +0000"},"done":true},"minecraft:recipes/tools/wooden_axe":{"criteria":{"has_stick":"2025-05-02 21:59:31 +0000"},"done":true},"minecraft:recipes/tools/wooden_shovel":{"criteria":{"has_stick":"2025-05-02 21:59:31 +0000"},"done":true},"minecraft:recipes/combat/wooden_sword":{"criteria":{"has_stick":"2025-05-02 21:59:31 +0000"},"done":true},"DataVersion":4082}